vim_edit/__init__.py
vim_edit/__version__.py
vim_edit/editor.py
vim_edit-1.0.1.dist-info/METADATA
vim_edit-1.0.1.dist-info/WHEEL
vim_edit-1.0.1.dist-info/top_level.txt
vim_edit-1.0.1.dist-info/RECORD
