Metadata-Version: 2.1
Name: vim-edit
Version: 1.0.1
Summary: Open file-like objects for editing in vim.
Home-page: https://github.com/foxyblue/vim-edit
Author: S. Williams-Wynn
Author-email: s.williamswynn.mail@gmail.com
License: UNKNOWN
Platform: UNKNOWN
Requires-Python: >=3.6
